proMAD/__init__.py
proMAD/config.py
proMAD/core.py
proMAD/cut.py
proMAD/report.py
proMAD/data/array/ARY007.json
proMAD/data/array/ARY015.json
proMAD/data/array/ARY022B.json
proMAD/data/array/ARY028.json
proMAD/data/templates/logo.png
proMAD/data/templates/short_report.tex
proMAD-0.3.2.dist-info/LICENSE.txt
proMAD-0.3.2.dist-info/METADATA
proMAD-0.3.2.dist-info/WHEEL
proMAD-0.3.2.dist-info/top_level.txt
proMAD-0.3.2.dist-info/zip-safe
proMAD-0.3.2.dist-info/RECORD
