Metadata-Version: 2.1
Name: proMAD
Version: 0.3.2
Summary: Semiquantitative densitometric measurement of protein microarrays
Home-page: https://proMAD.dev
Author: Anna Jaeschke; Hagen Eckert
Author-email: 
License: MIT
Download-URL: https://github.com/theia-dev/proMAD/archive/v0.3.2.zip
Keywords: protein,microarrays,densitometric
Platform: UNKNOWN
Classifier: Development Status :: 5 - Production/Stable
Classifier: Intended Audience :: Science/Research
Classifier: Topic :: Scientific/Engineering :: Bio-Informatics
Classifier: Topic :: Scientific/Engineering :: Image Recognition
Classifier: Topic :: Scientific/Engineering :: Information Analysis
Classifier: License :: OSI Approved :: MIT License
Classifier: Operating System :: OS Independent
Classifier: Programming Language :: Python :: 3.6
Classifier: Programming Language :: Python :: 3.7
Classifier: Programming Language :: Python :: 3.8
Classifier: Programming Language :: Python :: 3 :: Only
Requires-Python: ~=3.6
Requires-Dist: numpy
Requires-Dist: matplotlib
Requires-Dist: scipy
Requires-Dist: scikit-image
Requires-Dist: imageio
Requires-Dist: openpyxl
Requires-Dist: requests
Requires-Dist: ipython
Requires-Dist: xmltodict
Requires-Dist: jinja2
Requires-Dist: pylatexenc
